Workbook

Sheet Engine
A1: ATHENE — THE QUARTERLY ENGINE (stock & flow, every line from footed extracts)
A2: $ in millions. Blue = filed value (ATH financial supplements, sha in acquisition/manifest.csv). Black bold = formula. "check" rows show FAIL if an identity breaks. Yellow column = fill when 2Q26 publishes.
B4: 4Q24 | C4: 1Q25 | D4: 2Q25 | E4: 3Q25 | F4: 4Q25 | G4: 1Q26 | H4: 2Q26
A6: MONEY IN — BY CHANNEL
A7: Retail | B7: 7954 | C7: 9482 | D7: 7256 | E7: 10046 | F7: 7343 | G7: 7270
A8: Flow reinsurance | B8: 1029 | C8: 4933 | D8: 2031 | E8: 2542 | F8: 1665 | G8: 2603
A9: Funding agreements | B9: 5167 | C9: 11144 | D9: 11707 | E9: 9724 | F9: 2800 | G9: 8531
A10: Pension group annuities | B10: 47 | C10: 4 | D10: 1 | E10: 0 | F10: 746 | G10: 0
A11: Other spread products | B11: 0 | C11: 0 | D11: 237 | E11: 304 | F11: 133 | G11: 1343
A12: = Gross organic inflows | B12: =SUM(B7:B11) | C12: =SUM(C7:C11) | D12: =SUM(D7:D11) | E12: =SUM(E7:E11) | F12: =SUM(F7:F11) | G12: =SUM(G7:G11)
A13: Gross inorganic (block) inflows | B13: 0 | C13: 0 | D13: 0 | E13: 0 | F13: 1340 | G13: 0
A14: = TOTAL GROSS INFLOWS | B14: =B12+B13 | C14: =C12+C13 | D14: =D12+D13 | E14: =E12+E13 | F14: =F12+F13 | G14: =G12+G13
A15: reported total (filed) | B15: 14197 | C15: 25563 | D15: 21232 | E15: 22616 | F15: 14027 | G15: 19747
A16: check | B16: =IF(B14=B15,"OK","FAIL") | C16: =IF(C14=C15,"OK","FAIL") | D16: =IF(D14=D15,"OK","FAIL") | E16: =IF(E14=E15,"OK","FAIL") | F16: =IF(F14=F15,"OK","FAIL") | G16: =IF(G14=G15,"OK","FAIL")
A18: SAME MONEY, BY OWNER — the two cuts must agree
A19: Inflows attributable to Athene | B19: 8948 | C19: 20118 | D19: 15838 | E19: 17138 | F19: 10142 | G19: 15957
A20: Inflows attributable to ADIP (sidecar investors) | B20: 4343 | C20: 4956 | D20: 5019 | E20: 4962 | F20: 3515 | G20: 3453
A21: Inflows ceded to third-party reinsurers | B21: 906 | C21: 489 | D21: 375 | E21: 516 | F21: 370 | G21: 337
A22: = Total by owner | B22: =SUM(B19:B21) | C22: =SUM(C19:C21) | D22: =SUM(D19:D21) | E22: =SUM(E19:E21) | F22: =SUM(F19:F21) | G22: =SUM(G19:G21)
A23: check vs channel cut | B23: =IF(B22=B15,"OK","FAIL") | C23: =IF(C22=C15,"OK","FAIL") | D23: =IF(D22=D15,"OK","FAIL") | E23: =IF(E22=E15,"OK","FAIL") | F23: =IF(F22=F15,"OK","FAIL") | G23: =IF(G22=G15,"OK","FAIL")
A25: MONEY OUT
A26: Outflows attributable to Athene | B26: -5697 | C26: -7017 | D26: -5813 | E26: -9181 | F26: -7714 | G26: -8612
A27: Outflows attributable to ADIP | B27: -1439 | C27: -1375 | D27: -1417 | E27: -1457 | F27: -1554 | G27: -2156
A28: = Total gross outflows | B28: =B26+B27 | C28: =C26+C27 | D28: =D26+D27 | E28: =E26+E27 | F28: =F26+F27 | G28: =G26+G27
A29: reported total (filed) | B29: -7136 | C29: -8392 | D29: -7230 | E29: -10638 | F29: -9268 | G29: -10768
A30: check | B30: =IF(B28=B29,"OK","FAIL") | C30: =IF(C28=C29,"OK","FAIL") | D30: =IF(D28=D29,"OK","FAIL") | E30: =IF(E28=E29,"OK","FAIL") | F30: =IF(F28=F29,"OK","FAIL") | G30: =IF(G28=G29,"OK","FAIL")
A31: Athene outflows by type:
A32: Maturity-driven / contractual | B32: -2167 | C32: -3535 | D32: -2389 | E32: -5525 | F32: -3641 | G32: -4960
A33: Policyholder-driven | B33: -3530 | C33: -3482 | D33: -3424 | E33: -3656 | F33: -4073 | G33: -3652
A34: income-oriented (planned) | B34: -1661 | C34: -1680 | D34: -1609 | E34: -1660 | F34: -1922 | G34: -1845
A35: out of surrender charge (planned) | B35: -1131 | C35: -1058 | D35: -1025 | E35: -1093 | F35: -1198 | G35: -1089
A36: in surrender charge (unplanned) | B36: -738 | C36: -744 | D36: -790 | E36: -903 | F36: -953 | G36: -718
A37: check: policyholder = its three parts | B37: =IF(B33=SUM(B34:B36),"OK","FAIL") | C37: =IF(C33=SUM(C34:C36),"OK","FAIL") | D37: =IF(D33=SUM(D34:D36),"OK","FAIL") | E37: =IF(E33=SUM(E34:E36),"OK","FAIL") | F37: =IF(F33=SUM(F34:F36),"OK","FAIL") | G37: =IF(G33=SUM(G34:G36),"OK","FAIL")
A38: check: maturity + policyholder = Athene outflows | B38: =IF(B32+B33=B26,"OK","FAIL") | C38: =IF(C32+C33=C26,"OK","FAIL") | D38: =IF(D32+D33=D26,"OK","FAIL") | E38: =IF(E32+E33=E26,"OK","FAIL") | F38: =IF(F32+F33=F26,"OK","FAIL") | G38: =IF(G32+G33=G26,"OK","FAIL")
A40: NET FLOWS
A41: = Net flows (inflows + outflows) | B41: =B14+B28 | C41: =C14+C28 | D41: =D14+D28 | E41: =E14+E28 | F41: =F14+F28 | G41: =G14+G28
A42: reported net flows (filed) | B42: 7061 | C42: 17171 | D42: 14002 | E42: 11978 | F42: 4759 | G42: 8979
A43: check | B43: =IF(B41=B42,"OK","FAIL") | C43: =IF(C41=C42,"OK","FAIL") | D43: =IF(D41=D42,"OK","FAIL") | E43: =IF(E41=E42,"OK","FAIL") | F43: =IF(F41=F42,"OK","FAIL") | G43: =IF(G41=G42,"OK","FAIL")
A45: RESERVES — STOCK & FLOW (net reserve liabilities)
A46: Reserves — beginning | B46: 225899 | C46: 225926 | D46: 241666 | E46: 254572 | F46: 266451 | G46: 271233
A47: + Net inflows (Athene share) | B47: 9126 | C47: 20323 | D47: 16075 | E47: 17695 | F47: 10565 | G47: 16062
A48: − Net withdrawals | B48: -5697 | C48: -7017 | D48: -5813 | E48: -9181 | F48: -7714 | G48: -8612
A49: ± ACRA ownership changes | B49: -1774 | C49: 0 | D49: 0 | E49: 0 | F49: 0 | G49: 0
A50: + Other reserve changes (credited interest & misc) | B50: -1628 | C50: 2434 | D50: 2644 | E50: 3365 | F50: 1931 | G50: 506
A51: = Reserves — ending | B51: =SUM(B46:B50) | C51: =SUM(C46:C50) | D51: =SUM(D46:D50) | E51: =SUM(E46:E50) | F51: =SUM(F46:F50) | G51: =SUM(G46:G50)
A52: reported ending (filed) | B52: 225926 | C52: 241666 | D52: 254572 | E52: 266451 | F52: 271233 | G52: 279189
A53: check: identity | B53: =IF(B51=B52,"OK","FAIL") | C53: =IF(C51=C52,"OK","FAIL") | D53: =IF(D51=D52,"OK","FAIL") | E53: =IF(E51=E52,"OK","FAIL") | F53: =IF(F51=F52,"OK","FAIL") | G53: =IF(G51=G52,"OK","FAIL")
A54: check: continuity (begin = prior end) | B54: n/a | C54: =IF(C46=B52,"OK","FAIL") | D54: =IF(D46=C52,"OK","FAIL") | E54: =IF(E46=D52,"OK","FAIL") | F54: =IF(F46=E52,"OK","FAIL") | G54: =IF(G46=F52,"OK","FAIL")
A56: THE SIDECAR LEDGER — ACRA noncontrolling interests reserves
A57: ACRA reserves — beginning | B57: 68092 | C57: 72164 | D57: 76842 | E57: 81809 | F57: 86826 | G57: 89725
A58: + Inflows | B58: 4418 | C58: 5011 | D58: 5091 | E58: 5167 | F58: 3723 | G58: 3470
A59: − Withdrawals | B59: -1439 | C59: -1375 | D59: -1417 | E59: -1457 | F59: -1554 | G59: -2156
A60: ± ACRA ownership changes | B60: 1774 | C60: 0 | D60: 0 | E60: 0 | F60: 0 | G60: 0
A61: + Other reserve changes | B61: -681 | C61: 1042 | D61: 1293 | E61: 1307 | F61: 730 | G61: 279
A62: = ACRA reserves — ending | B62: =SUM(B57:B61) | C62: =SUM(C57:C61) | D62: =SUM(D57:D61) | E62: =SUM(E57:E61) | F62: =SUM(F57:F61) | G62: =SUM(G57:G61)
A63: reported ending (filed) | B63: 72164 | C63: 76842 | D63: 81809 | E63: 86826 | F63: 89725 | G63: 91318
A64: check | B64: =IF(B62=B63,"OK","FAIL") | C64: =IF(C62=C63,"OK","FAIL") | D64: =IF(D62=D63,"OK","FAIL") | E64: =IF(E62=E63,"OK","FAIL") | F64: =IF(F62=F63,"OK","FAIL") | G64: =IF(G62=G63,"OK","FAIL")
A66: RESERVE STOCK BY PRODUCT (period-ends / year-ends)
A67: Indexed annuities | B67: 82711 | F67: 87322 | G67: 86377
A68: Fixed rate annuities | B68: 62705 | F68: 77774 | G68: 82324
A69: = Total deferred annuities | B69: =B67+B68 | C69: =C67+C68 | D69: =D67+D68 | E69: =E67+E68 | F69: =F67+F68 | G69: =G67+G68
A70: Pension group annuities | B70: 24986 | F70: 25088 | G70: 24249
A71: Payout annuities | B71: 4701 | F71: 5066 | G71: 5239
A72: Funding agreements (the runnable slice) | B72: 47384 | F72: 71433 | G72: 75962
A73: Life and other | B73: 3439 | F73: 4550 | G73: 5038
A74: = Total net reserve liabilities | B74: =B69+SUM(B70:B73) | C74: =C69+SUM(C70:C73) | D74: =D69+SUM(D70:D73) | E74: =E69+SUM(E70:E73) | F74: =F69+SUM(F70:F73) | G74: =G69+SUM(G70:G73)
A75: reported total (filed) | B75: 225926 | F75: 271233 | G75: 279189
A76: check (only where period-end filed) | B76: =IF(B75="","n/a",IF(B74=B75,"OK","FAIL")) | C76: =IF(C75="","n/a",IF(C74=C75,"OK","FAIL")) | D76: =IF(D75="","n/a",IF(D74=D75,"OK","FAIL")) | E76: =IF(E75="","n/a",IF(E74=E75,"OK","FAIL")) | F76: =IF(F75="","n/a",IF(F74=F75,"OK","FAIL")) | G76: =IF(G75="","n/a",IF(G74=G75,"OK","FAIL"))
A78: THE INCOME ENGINE — spread related earnings
A79: Fixed income & other net investment income | B79: 2914 | C79: 2916 | D79: 3180 | E79: 3425 | F79: 3505 | G79: 3551
A80: Alternatives net investment income | B80: 269 | C80: 315 | D80: 319 | E80: 321 | F80: 344 | G80: 210
A81: = Net investment earnings | B81: =B79+B80 | C81: =C79+C80 | D81: =D79+D80 | E81: =E79+E80 | F81: =F79+F80 | G81: =G79+G80
A82: + Strategic capital management fees | B82: 29 | C82: 29 | D82: 32 | E82: 35 | F82: 35 | G82: 36
A83: − Cost of funds (what the float costs) | B83: -2116 | C83: -2210 | D83: -2470 | E83: -2661 | F83: -2742 | G83: -2807
A84: = NET INVESTMENT SPREAD | B84: =SUM(B81:B83) | C84: =SUM(C81:C83) | D84: =SUM(D81:D83) | E84: =SUM(E81:E83) | F84: =SUM(F81:F83) | G84: =SUM(G81:G83)
A85: reported (filed) | B85: 1096 | C85: 1050 | D85: 1061 | E85: 1120 | F85: 1142 | G85: 990
A86: check | B86: =IF(B84=B85,"OK","FAIL") | C86: =IF(C84=C85,"OK","FAIL") | D86: =IF(D84=D85,"OK","FAIL") | E86: =IF(E84=E85,"OK","FAIL") | F86: =IF(F84=F85,"OK","FAIL") | G86: =IF(G84=G85,"OK","FAIL")
A87: − Other operating expenses | B87: -121 | C87: -116 | D87: -109 | E87: -108 | F87: -119 | G87: -118
A88: − Interest & other financing costs | B88: -137 | C88: -130 | D88: -132 | E88: -140 | F88: -158 | G88: -153
A89: = SPREAD RELATED EARNINGS | B89: =B84+B87+B88 | C89: =C84+C87+C88 | D89: =D84+D87+D88 | E89: =E84+E87+E88 | F89: =F84+F87+F88 | G89: =G84+G87+G88
A90: reported (filed) | B90: 838 | C90: 804 | D90: 820 | E90: 872 | F90: 865 | G90: 719
A91: check | B91: =IF(B89=B90,"OK","FAIL") | C91: =IF(C89=C90,"OK","FAIL") | D91: =IF(D89=D90,"OK","FAIL") | E91: =IF(E89=E90,"OK","FAIL") | F91: =IF(F89=F90,"OK","FAIL") | G91: =IF(G89=G90,"OK","FAIL")
A93: THE RATES (annualized, as filed)
A94: Earned — fixed income & other | B94: 0.05 | C94: 0.048 | D94: 0.0497 | E94: 0.0512 | F94: 0.0508 | G94: 0.0504
A95: Earned — alternatives | B95: 0.0925 | C95: 0.1008 | D95: 0.0986 | E95: 0.0988 | F95: 0.1019 | G95: 0.0579
A96: Earned — total | B96: 0.052 | C96: 0.0506 | D96: 0.0521 | E96: 0.0534 | F96: 0.0532 | G96: 0.0508
A97: Cost of funds | B97: -0.0346 | C97: -0.0346 | D97: -0.0368 | E97: -0.0379 | F97: -0.0379 | G97: -0.0379
A98: NET INVESTMENT SPREAD % | B98: 0.0179 | C98: 0.0165 | D98: 0.0158 | E98: 0.016 | F98: 0.0158 | G98: 0.0134
A99: SRE margin % | B99: 0.0137 | C99: 0.0126 | D99: 0.0122 | E99: 0.0124 | F99: 0.012 | G99: 0.0097
A101: THE DENOMINATOR & DERIVED
A102: Average net invested assets — fixed income | B102: 233153 | C102: 242999 | D102: 255789 | E102: 267607 | F102: 275769 | G102: 281872
A103: Average net invested assets — alternatives | B103: 11643 | C103: 12506 | D103: 12914 | E103: 13000 | F103: 13526 | G103: 14480
A104: = Average net invested assets | B104: =B102+B103 | C104: =C102+C103 | D104: =D102+D103 | E104: =E102+E103 | F104: =F102+F103 | G104: =G102+G103
A105: Derived NIS % (spread ×4 ÷ avg assets) | B105: =IF(OR(B104=0,B104=""),"",B84*4/B104) | C105: =IF(OR(C104=0,C104=""),"",C84*4/C104) | D105: =IF(OR(D104=0,D104=""),"",D84*4/D104) | E105: =IF(OR(E104=0,E104=""),"",E84*4/E104) | F105: =IF(OR(F104=0,F104=""),"",F84*4/F104) | G105: =IF(OR(G104=0,G104=""),"",G84*4/G104)
A106: check vs filed NIS % (±5bp rounding) | B106: =IF(B105="","n/a",IF(ABS(B105-B98)<0.0005,"OK","FAIL")) | C106: =IF(C105="","n/a",IF(ABS(C105-C98)<0.0005,"OK","FAIL")) | D106: =IF(D105="","n/a",IF(ABS(D105-D98)<0.0005,"OK","FAIL")) | E106: =IF(E105="","n/a",IF(ABS(E105-E98)<0.0005,"OK","FAIL")) | F106: =IF(F105="","n/a",IF(ABS(F105-F98)<0.0005,"OK","FAIL")) | G106: =IF(G105="","n/a",IF(ABS(G105-G98)<0.0005,"OK","FAIL"))
A108: THE PORTFOLIO — STATUTORY BOND BOOK, THE FEATURES WE BUILT (year-ends; footed to the dollar)
A109: Total bond book (BACV)
A110: NAIC 1 (AAA…A−)
A111: NAIC 2 (BBB band)
A112: Below investment grade (NAIC 3–6)
...

Sheet Engine-FY
A1: ATHENE — THE ANNUAL ENGINE (same rows; FY2023 from 10-K, FY2024/25 from Q4 supplement YTD, cross-gated)
A2: Blue = filed value (ahl-10k-fy2025 MD&A + ATH Q4'25 supplement full-year columns; both sources agree exactly where they overlap). "FY25 Σq" = live sum over the Engine tab — its check must read OK. Blank FY2023 cells = row published only in supplements (older ones are glyph-encoded; decoder parked); their checks read n/a.
B4: FY2023 | C4: FY2024 | D4: FY2025 | E4: FY25 Σq | F4: src-check
A6: MONEY IN — BY CHANNEL
A7: Retail | B7: 35293 | C7: 35764 | D7: 34127 | E7: =SUM(Engine!C7:F7) | F7: =IF(D7="","n/a",IF(E7=D7,"OK","FAIL"))
A8: Flow reinsurance | B8: 10547 | C8: 5573 | D8: 11171 | E8: =SUM(Engine!C8:F8) | F8: =IF(D8="","n/a",IF(E8=D8,"OK","FAIL"))
A9: Funding agreements | B9: 7193 | C9: 28748 | D9: 35375 | E9: =SUM(Engine!C9:F9) | F9: =IF(D9="","n/a",IF(E9=D9,"OK","FAIL"))
A10: Pension group annuities | B10: 10374 | C10: 918 | D10: 751 | E10: =SUM(Engine!C10:F10) | F10: =IF(D10="","n/a",IF(E10=D10,"OK","FAIL"))
A11: Other spread products | B11: 0 | C11: 0 | D11: 674 | E11: =SUM(Engine!C11:F11) | F11: =IF(D11="","n/a",IF(E11=D11,"OK","FAIL"))
A12: = Gross organic inflows | B12: =SUM(B7:B11) | C12: =SUM(C7:C11) | D12: =SUM(D7:D11)
A13: Gross inorganic (block) inflows | B13: 2214 | C13: 0 | D13: 1340 | E13: =SUM(Engine!C13:F13) | F13: =IF(D13="","n/a",IF(E13=D13,"OK","FAIL"))
A14: = TOTAL GROSS INFLOWS | B14: =B12+B13 | C14: =C12+C13 | D14: =D12+D13
A15: reported total (filed) | B15: 65621 | C15: 71003 | D15: 83438 | E15: =SUM(Engine!C15:F15) | F15: =IF(D15="","n/a",IF(E15=D15,"OK","FAIL"))
A16: check | B16: =IF(B15="","n/a",IF(B14=B15,"OK","FAIL")) | C16: =IF(C15="","n/a",IF(C14=C15,"OK","FAIL")) | D16: =IF(D15="","n/a",IF(D14=D15,"OK","FAIL"))
A18: SAME MONEY, BY OWNER — the two cuts must agree
A19: Inflows attributable to Athene | B19: 43000 | C19: 49084 | D19: 63236 | E19: =SUM(Engine!C19:F19) | F19: =IF(D19="","n/a",IF(E19=D19,"OK","FAIL"))
A20: Inflows attributable to ADIP (sidecar investors) | B20: 22621 | C20: 17848 | D20: 18452 | E20: =SUM(Engine!C20:F20) | F20: =IF(D20="","n/a",IF(E20=D20,"OK","FAIL"))
A21: Inflows ceded to third-party reinsurers | B21: 0 | C21: 4071 | D21: 1750 | E21: =SUM(Engine!C21:F21) | F21: =IF(D21="","n/a",IF(E21=D21,"OK","FAIL"))
A22: = Total by owner | B22: =SUM(B19:B21) | C22: =SUM(C19:C21) | D22: =SUM(D19:D21)
A23: check vs channel cut | B23: =IF(B15="","n/a",IF(B22=B15,"OK","FAIL")) | C23: =IF(C15="","n/a",IF(C22=C15,"OK","FAIL")) | D23: =IF(D15="","n/a",IF(D22=D15,"OK","FAIL"))
A25: MONEY OUT
A26: Outflows attributable to Athene | B26: -28763 | C26: -27248 | D26: -29725 | E26: =SUM(Engine!C26:F26) | F26: =IF(D26="","n/a",IF(E26=D26,"OK","FAIL"))
A27: Outflows attributable to ADIP | B27: -5105 | C27: -6221 | D27: -5803 | E27: =SUM(Engine!C27:F27) | F27: =IF(D27="","n/a",IF(E27=D27,"OK","FAIL"))
A28: = Total gross outflows | B28: =B26+B27 | C28: =C26+C27 | D28: =D26+D27
A29: reported total (filed) | B29: -33868 | C29: -33469 | D29: -35528 | E29: =SUM(Engine!C29:F29) | F29: =IF(D29="","n/a",IF(E29=D29,"OK","FAIL"))
A30: check | B30: =IF(B29="","n/a",IF(B28=B29,"OK","FAIL")) | C30: =IF(C29="","n/a",IF(C28=C29,"OK","FAIL")) | D30: =IF(D29="","n/a",IF(D28=D29,"OK","FAIL"))
A31: Athene outflows by type:
A32: Maturity-driven / contractual | C32: -12096 | D32: -15090 | E32: =SUM(Engine!C32:F32) | F32: =IF(D32="","n/a",IF(E32=D32,"OK","FAIL"))
A33: Policyholder-driven | C33: -15152 | D33: -14635 | E33: =SUM(Engine!C33:F33) | F33: =IF(D33="","n/a",IF(E33=D33,"OK","FAIL"))
A34: income-oriented (planned) | C34: -6427 | D34: -6871 | E34: =SUM(Engine!C34:F34) | F34: =IF(D34="","n/a",IF(E34=D34,"OK","FAIL"))
A35: out of surrender charge (planned) | C35: -5598 | D35: -4374 | E35: =SUM(Engine!C35:F35) | F35: =IF(D35="","n/a",IF(E35=D35,"OK","FAIL"))
A36: in surrender charge (unplanned) | C36: -3127 | D36: -3390 | E36: =SUM(Engine!C36:F36) | F36: =IF(D36="","n/a",IF(E36=D36,"OK","FAIL"))
A37: check: policyholder = its three parts | B37: =IF(B36="","n/a",IF(B33=SUM(B34:B36),"OK","FAIL")) | C37: =IF(C36="","n/a",IF(C33=SUM(C34:C36),"OK","FAIL")) | D37: =IF(D36="","n/a",IF(D33=SUM(D34:D36),"OK","FAIL"))
A38: check: maturity + policyholder = Athene outflows | B38: =IF(B26="","n/a",IF(B32+B33=B26,"OK","FAIL")) | C38: =IF(C26="","n/a",IF(C32+C33=C26,"OK","FAIL")) | D38: =IF(D26="","n/a",IF(D32+D33=D26,"OK","FAIL"))
A40: NET FLOWS
A41: = Net flows (inflows + outflows) | B41: =B14+B28 | C41: =C14+C28 | D41: =D14+D28
A42: reported net flows (filed) | B42: 31753 | C42: 37534 | D42: 47910 | E42: =SUM(Engine!C42:F42) | F42: =IF(D42="","n/a",IF(E42=D42,"OK","FAIL"))
A43: check | B43: =IF(B42="","n/a",IF(B41=B42,"OK","FAIL")) | C43: =IF(C42="","n/a",IF(C41=C42,"OK","FAIL")) | D43: =IF(D42="","n/a",IF(D41=D42,"OK","FAIL"))
A45: RESERVES — STOCK & FLOW (net reserve liabilities)
A46: Reserves — beginning | C46: 199289 | D46: 225926 | E46: =SUM(Engine!C46:F46) | F46: =IF(D46="","n/a",IF(E46=D46,"OK","FAIL"))
A47: + Net inflows (Athene share) | C47: 49857 | D47: 64658 | E47: =SUM(Engine!C47:F47) | F47: =IF(D47="","n/a",IF(E47=D47,"OK","FAIL"))
A48: − Net withdrawals | C48: -27248 | D48: -29725 | E48: =SUM(Engine!C48:F48) | F48: =IF(D48="","n/a",IF(E48=D48,"OK","FAIL"))
A49: ± ACRA ownership changes | C49: -1774 | D49: 0 | E49: =SUM(Engine!C49:F49) | F49: =IF(D49="","n/a",IF(E49=D49,"OK","FAIL"))
A50: + Other reserve changes (credited interest & misc) | C50: 5802 | D50: 10374 | E50: =SUM(Engine!C50:F50) | F50: =IF(D50="","n/a",IF(E50=D50,"OK","FAIL"))
A51: = Reserves — ending | B51: =SUM(B46:B50) | C51: =SUM(C46:C50) | D51: =SUM(D46:D50)
A52: reported ending (filed) | C52: 225926 | D52: 271233 | E52: =SUM(Engine!C52:F52) | F52: =IF(D52="","n/a",IF(E52=D52,"OK","FAIL"))
A53: check: identity | B53: =IF(B52="","n/a",IF(B51=B52,"OK","FAIL")) | C53: =IF(C52="","n/a",IF(C51=C52,"OK","FAIL")) | D53: =IF(D52="","n/a",IF(D51=D52,"OK","FAIL"))
A54: check: continuity (begin = prior end) | B54: n/a | C54: =IF(B52="","n/a",IF(C46=B52,"OK","FAIL")) | D54: =IF(C52="","n/a",IF(D46=C52,"OK","FAIL"))
A56: THE SIDECAR LEDGER — ACRA noncontrolling interests reserves
A57: ACRA reserves — beginning | C57: 56651 | D57: 72164 | E57: =SUM(Engine!C57:F57) | F57: =IF(D57="","n/a",IF(E57=D57,"OK","FAIL"))
A58: + Inflows | C58: 18162 | D58: 18992 | E58: =SUM(Engine!C58:F58) | F58: =IF(D58="","n/a",IF(E58=D58,"OK","FAIL"))
A59: − Withdrawals | C59: -6221 | D59: -5803 | E59: =SUM(Engine!C59:F59) | F59: =IF(D59="","n/a",IF(E59=D59,"OK","FAIL"))
A60: ± ACRA ownership changes | C60: 1774 | D60: 0 | E60: =SUM(Engine!C60:F60) | F60: =IF(D60="","n/a",IF(E60=D60,"OK","FAIL"))
A61: + Other reserve changes | C61: 1798 | D61: 4372 | E61: =SUM(Engine!C61:F61) | F61: =IF(D61="","n/a",IF(E61=D61,"OK","FAIL"))
A62: = ACRA reserves — ending | B62: =SUM(B57:B61) | C62: =SUM(C57:C61) | D62: =SUM(D57:D61)
A63: reported ending (filed) | C63: 72164 | D63: 89725 | E63: =SUM(Engine!C63:F63) | F63: =IF(D63="","n/a",IF(E63=D63,"OK","FAIL"))
A64: check | B64: =IF(B63="","n/a",IF(B62=B63,"OK","FAIL")) | C64: =IF(C63="","n/a",IF(C62=C63,"OK","FAIL")) | D64: =IF(D63="","n/a",IF(D62=D63,"OK","FAIL"))
A66: RESERVE STOCK BY PRODUCT (period-ends / year-ends)
A67: Indexed annuities | C67: 82711 | D67: 87322 | E67: =SUM(Engine!C67:F67) | F67: =IF(D67="","n/a",IF(E67=D67,"OK","FAIL"))
A68: Fixed rate annuities | C68: 62705 | D68: 77774 | E68: =SUM(Engine!C68:F68) | F68: =IF(D68="","n/a",IF(E68=D68,"OK","FAIL"))
A69: = Total deferred annuities | B69: =B67+B68 | C69: =C67+C68 | D69: =D67+D68
A70: Pension group annuities | C70: 24986 | D70: 25088 | E70: =SUM(Engine!C70:F70) | F70: =IF(D70="","n/a",IF(E70=D70,"OK","FAIL"))
A71: Payout annuities | C71: 4701 | D71: 5066 | E71: =SUM(Engine!C71:F71) | F71: =IF(D71="","n/a",IF(E71=D71,"OK","FAIL"))
A72: Funding agreements (the runnable slice) | C72: 47384 | D72: 71433 | E72: =SUM(Engine!C72:F72) | F72: =IF(D72="","n/a",IF(E72=D72,"OK","FAIL"))
A73: Life and other | C73: 3439 | D73: 4550 | E73: =SUM(Engine!C73:F73) | F73: =IF(D73="","n/a",IF(E73=D73,"OK","FAIL"))
A74: = Total net reserve liabilities | B74: =B69+SUM(B70:B73) | C74: =C69+SUM(C70:C73) | D74: =D69+SUM(D70:D73)
A75: reported total (filed) | C75: 225926 | D75: 271233 | E75: =SUM(Engine!C75:F75) | F75: =IF(D75="","n/a",IF(E75=D75,"OK","FAIL"))
A76: check (only where period-end filed) | B76: =IF(B75="","n/a",IF(B75="","n/a",IF(B74=B75,"OK","FAIL"))) | C76: =IF(C75="","n/a",IF(C75="","n/a",IF(C74=C75,"OK","FAIL"))) | D76: =IF(D75="","n/a",IF(D75="","n/a",IF(D74=D75,"OK","FAIL")))
A78: THE INCOME ENGINE — spread related earnings
A79: Fixed income & other net investment income | B79: 8744 | C79: 10811 | D79: 13026 | E79: =SUM(Engine!C79:F79) | F79: =IF(D79="","n/a",IF(E79=D79,"OK","FAIL"))
A80: Alternatives net investment income | B80: 864 | C80: 939 | D80: 1299 | E80: =SUM(Engine!C80:F80) | F80: =IF(D80="","n/a",IF(E80=D80,"OK","FAIL"))
A81: = Net investment earnings | B81: =B79+B80 | C81: =C79+C80 | D81: =D79+D80
A82: + Strategic capital management fees | B82: 72 | C82: 105 | D82: 131 | E82: =SUM(Engine!C82:F82) | F82: =IF(D82="","n/a",IF(E82=D82,"OK","FAIL"))
A83: − Cost of funds (what the float costs) | B83: -5650 | C83: -7702 | D83: -10083 | E83: =SUM(Engine!C83:F83) | F83: =IF(D83="","n/a",IF(E83=D83,"OK","FAIL"))
A84: = NET INVESTMENT SPREAD | B84: =SUM(B81:B83) | C84: =SUM(C81:C83) | D84: =SUM(D81:D83)
A85: reported (filed) | B85: 4030 | C85: 4153 | D85: 4373 | E85: =SUM(Engine!C85:F85) | F85: =IF(D85="","n/a",IF(E85=D85,"OK","FAIL"))
A86: check | B86: =IF(B85="","n/a",IF(B84=B85,"OK","FAIL")) | C86: =IF(C85="","n/a",IF(C84=C85,"OK","FAIL")) | D86: =IF(D85="","n/a",IF(D84=D85,"OK","FAIL"))
A87: − Other operating expenses | B87: -487 | C87: -467 | D87: -452 | E87: =SUM(Engine!C87:F87) | F87: =IF(D87="","n/a",IF(E87=D87,"OK","FAIL"))
A88: − Interest & other financing costs | B88: -436 | C88: -465 | D88: -560 | E88: =SUM(Engine!C88:F88) | F88: =IF(D88="","n/a",IF(E88=D88,"OK","FAIL"))
A89: = SPREAD RELATED EARNINGS | B89: =B84+B87+B88 | C89: =C84+C87+C88 | D89: =D84+D87+D88
A90: reported (filed) | B90: 3107 | C90: 3221 | D90: 3361 | E90: =SUM(Engine!C90:F90) | F90: =IF(D90="","n/a",IF(E90=D90,"OK","FAIL"))
A91: check | B91: =IF(B90="","n/a",IF(B89=B90,"OK","FAIL")) | C91: =IF(C90="","n/a",IF(C89=C90,"OK","FAIL")) | D91: =IF(D90="","n/a",IF(D89=D90,"OK","FAIL"))
A93: THE RATES (annualized, as filed)
A94: Earned — fixed income & other | C94: 0.0487 | D94: 0.0501
A95: Earned — alternatives | C95: 0.0803 | D95: 0.1001
A96: Earned — total | C96: 0.0503 | D96: 0.0525
A97: Cost of funds | C97: -0.0329 | D97: -0.0369
A98: NET INVESTMENT SPREAD % | C98: 0.0178 | D98: 0.0161
A99: SRE margin % | C99: 0.0138 | D99: 0.0123
A101: THE DENOMINATOR & DERIVED
A102: Average net invested assets — fixed income | C102: 222122 | D102: 259952 | E102: =SUM(Engine!C102:F102) | F102: =IF(D102="","n/a",IF(E102=D102,"OK","FAIL"))
A103: Average net invested assets — alternatives | C103: 11687 | D103: 12976 | E103: =SUM(Engine!C103:F103) | F103: =IF(D103="","n/a",IF(E103=D103,"OK","FAIL"))
A104: = Average net invested assets | B104: =B102+B103 | C104: =C102+C103 | D104: =D102+D103
A105: Derived NIS % (spread ×1 ÷ avg assets) | B105: =IF(OR(B104=0,B104=""),"",B84*1/B104) | C105: =IF(OR(C104=0,C104=""),"",C84*1/C104) | D105: =IF(OR(D104=0,D104=""),"",D84*1/D104)
A106: check vs filed NIS % (±5bp rounding) | B106: =IF(B98="","n/a",IF(B105="","n/a",IF(ABS(B105-B98)<0.0005,"OK","FAIL"))) | C106: =IF(C98="","n/a",IF(C105="","n/a",IF(ABS(C105-C98)<0.0005,"OK","FAIL"))) | D106: =IF(D98="","n/a",IF(D105="","n/a",IF(ABS(D105-D98)<0.0005,"OK","FAIL")))
A108: THE PORTFOLIO — STATUTORY BOND BOOK, THE FEATURES WE BUILT (year-ends; footed to the dollar)
A109: Total bond book (BACV) | B109: 75192.554 | C109: 130962.44 | D109: 158852.4 | E109: =SUM(Engine!C109:F109) | F109: =IF(D109="","n/a",IF(E109=D109,"OK","FAIL"))
A110: NAIC 1 (AAA…A−) | B110: 43543.526 | C110: 77605.751 | D110: 94173.706 | E110: =SUM(Engine!C110:F110) | F110: =IF(D110="","n/a",IF(E110=D110,"OK","FAIL"))
A111: NAIC 2 (BBB band) | B111: 28853.903 | C111: 49115.707 | D111: 60081.028 | E111: =SUM(Engine!C111:F111) | F111: =IF(D111="","n/a",IF(E111=D111,"OK","FAIL"))
A112: Below investment grade (NAIC 3–6) | B112: 2795.1244 | C112: 4240.9841 | D112: 4597.6619 | E112: =SUM(Engine!C112:F112) | F112: =IF(D112="","n/a",IF(E112=D112,"OK","FAIL"))
...

Sheet Checks
A1: LIVE CHECKS — this cell must read 0
A3: Number of failing identity checks across Engine + Engine-FY: | B3: =COUNTIF('Engine'!B16,"FAIL")+COUNTIF('Engine'!C16,"FAIL")+COUNTIF('Engine'!D16,"FAIL")+COUNTIF('Engine'!E16,"FAIL")+COUNTIF('Engine'!F16,"FAIL")+COUNTIF('Engine'!G16,"FAIL")+COUNTIF('Engine'!B23,"FAIL")+COUNTIF('Engine'!C23,"FAIL")+COUNTIF('Engine'!D23,"FAIL")+COUNTIF('Engine'!E23,"FAIL")+COUNTIF('Engine'!F23,"FAIL")+COUNTIF('Engine'!G23,"FAIL")+COUNTIF('Engine'!B30,"FAIL")+COUNTIF('Engine'!C30,"FAIL")+COUNTIF('Engine'!D30,"FAIL")+COUNTIF('Engine'!E30,"FAIL")+COUNTIF('Engine'!F30,"FAIL")+COUNTIF('Engine'!G30,"FAIL")+COUNTIF('Engine'!B37,"FAIL")+COUNTIF('Engine'!C37,"FAIL")+COUNTIF('Engine'!D37,"FAIL")+COUNTIF('Engine'!E37,"FAIL")+COUNTIF('Engine'!F37,"FAIL")+COUNTIF('Engine'!G37,"FAIL")+COUNTIF('Engine'!B38,"FAIL")+COUNTIF('Engine'!C38,"FAIL")+COUNTIF('Engine'!D38,"FAIL")+COUNTIF('Engine'!E38,"FAIL")+COUNTIF('Engine'!F38,"FAIL")+COUNTIF('Engine'!G38,"FAIL")+COUNTIF('Engine'!B43,"FAIL")+COUNTIF('Engine'!C43,"FAIL")+COUNTIF('Engine'!D43,"FAIL")+COUNTIF('Engine'!E43,"FAIL")+COUNTIF('Engine'!F43,"FAIL")+COUNTIF('Engine'!G43,"FAIL")+COUNTIF('Engine'!B53,"FAIL")+COUNTIF('Engine'!C53,"FAIL")+COUNTIF('Engine'!D53,"FAIL")+COUNTIF('Engine'!E53,"FAIL")+COUNTIF('Engine'!F53,"FAIL")+COUNTIF('Engine'!G53,"FAIL")+COUNTIF('Engine'!C54,"FAIL")+COUNTIF('Engine'!D54,"FAIL")+COUNTIF('Engine'!E54,"FAIL")+COUNTIF('Engine'!F54,"FAIL")+COUNTIF('Engine'!G54,"FAIL")+COUNTIF('Engine'!B64,"FAIL")+COUNTIF('Engine'!C64,"FAIL")+COUNTIF('Engine'!D64,"FAIL")+COUNTIF('Engine'!E64,"FAIL")+COUNTIF('Engine'!F64,"FAIL")+COUNTIF('Engine'!G64,"FAIL")+COUNTIF('Engine'!B76,"FAIL")+COUNTIF('Engine'!C76,"FAIL")+COUNTIF('Engine'!D76,"FAIL")+COUNTIF('Engine'!E76,"FAIL")+COUNTIF('Engine'!F76,"FAIL")+COUNTIF('Engine'!G76,"FAIL")+COUNTIF('Engine'!B86,"FAIL")+COUNTIF('Engine'!C86,"FAIL")+COUNTIF('Engine'!D86,"FAIL")+COUNTIF('Engine'!E86,"FAIL")+COUNTIF('Engine'!F86,"FAIL")+COUNTIF('Engine'!G86,"FAIL")+COUNTIF('Engine'!B91,"FAIL")+COUNTIF('Engine'!C91,"FAIL")+COUNTIF('Engine'!D91,"FAIL")+COUNTIF('Engine'!E91,"FAIL")+COUNTIF('Engine'!F91,"FAIL")+COUNTIF('Engine'!G91,"FAIL")+COUNTIF('Engine'!B106,"FAIL")+COUNTIF('Engine'!C106,"FAIL")+COUNTIF('Engine'!D106,"FAIL")+COUNTIF('Engine'!E106,"FAIL")+COUNTIF('Engine'!F106,"FAIL")+COUNTIF('Engine'!G106,"FAIL")+COUNTIF('Engine'!B113,"FAIL")+COUNTIF('Engine'!C113,"FAIL")+COUNTIF('Engine'!D113,"FAIL")+COUNTIF('Engine'!E113,"FAIL")+COUNTIF('Engine'!F113,"FAIL")+COUNTIF('Engine'!G113,"FAIL")+COUNTIF('Engine'!B120,"FAIL")+COUNTIF('Engine'!C120,"FAIL")+COUNTIF('Engine'!D120,"FAIL")+COUNTIF('Engine'!E120,"FAIL")+COUNTIF('Engine'!F120,"FAIL")+COUNTIF('Engine'!G120,"FAIL")+COUNTIF('Engine'!B127,"FAIL")+COUNTIF('Engine'!C127,"FAIL")+COUNTIF('Engine'!D127,"FAIL")+COUNTIF('Engine'!E127,"FAIL")+COUNTIF('Engine'!F127,"FAIL")+COUNTIF('Engine'!G127,"FAIL")+COUNTIF('Engine'!B149,"FAIL")+COUNTIF('Engine'!C149,"FAIL")+COUNTIF('Engine'!D149,"FAIL")+COUNTIF('Engine'!E149,"FAIL")+COUNTIF('Engine'!F149,"FAIL")+COUNTIF('Engine'!G149,"FAIL")+COUNTIF('Engine'!B164,"FAIL")+COUNTIF('Engine'!C164,"FAIL")+COUNTIF('Engine'!D164,"FAIL")+COUNTIF('Engine'!E164,"FAIL")+COUNTIF('Engine'!F164,"FAIL")+COUNTIF('Engine'!G164,"FAIL")+COUNTIF('Engine'!B176,"FAIL")+COUNTIF('Engine'!C176,"FAIL")+COUNTIF('Engine'!D176,"FAIL")+COUNTIF('Engine'!E176,"FAIL")+COUNTIF('Engine'!F176,"FAIL")+COUNTIF('Engine'!G176,"FAIL")+COUNTIF('Engine'!B188,"FAIL")+COUNTIF('Engine'!C188,"FAIL")+COUNTIF('Engine'!D188,"FAIL")+COUNTIF('Engine'!E188,"FAIL")+COUNTIF('Engine'!F188,"FAIL")+COUNTIF('Engine'!G188,"FAIL")+COUNTIF('Engine'!B194,"FAIL")+COUNTIF('Engine'!C194,"FAIL")+COUNTIF('Engine'!D194,"FAIL")+COUNTIF('Engine'!E194,"FAIL")+COUNTIF('Engine'!F194,"FAIL")+COUNTIF('Engine'!G194,"FAIL")+COUNTIF('Engine'!B202,"FAIL")+COUNTIF('Engine'!C202,"FAIL")+COUNTIF('Engine'!D202,"FAIL")+COUNTIF('Engine'!E202,"FAIL")+COUNTIF('Engine'!F202,"FAIL")+COUNTIF('Engine'!G202,"FAIL")+COUNTIF('Engine'!B206,"FAIL")+COUNTIF('Engine'!C206,"FAIL")+COUNTIF('Engine'!D206,"FAIL")+COUNTIF('Engine'!E206,"FAIL")+COUNTIF('Engine'!F206,"FAIL")+COUNTIF('Engine'!G206,"FAIL")+COUNTIF('Engine-FY'!F7,"FAIL")+COUNTIF('Engine-FY'!F8,"FAIL")+COUNTIF('Engine-FY'!F9,"FAIL")+COUNTIF('Engine-FY'!F10,"FAIL")+COUNTIF('Engine-FY'!F11,"FAIL")+COUNTIF('Engine-FY'!F13,"FAIL")+COUNTIF('Engine-FY'!F15,"FAIL")+COUNTIF('Engine-FY'!B16,"FAIL")+COUNTIF('Engine-FY'!C16,"FAIL")+COUNTIF('Engine-FY'!D16,"FAIL")+COUNTIF('Engine-FY'!F19,"FAIL")+COUNTIF('Engine-FY'!F20,"FAIL")+COUNTIF('Engine-FY'!F21,"FAIL")+COUNTIF('Engine-FY'!B23,"FAIL")+COUNTIF('Engine-FY'!C23,"FAIL")+COUNTIF('Engine-FY'!D23,"FAIL")+COUNTIF('Engine-FY'!F26,"FAIL")+COUNTIF('Engine-FY'!F27,"FAIL")+COUNTIF('Engine-FY'!F29,"FAIL")+COUNTIF('Engine-FY'!B30,"FAIL")+COUNTIF('Engine-FY'!C30,"FAIL")+COUNTIF('Engine-FY'!D30,"FAIL")+COUNTIF('Engine-FY'!F32,"FAIL")+COUNTIF('Engine-FY'!F33,"FAIL")+COUNTIF('Engine-FY'!F34,"FAIL")+COUNTIF('Engine-FY'!F35,"FAIL")+COUNTIF('Engine-FY'!F36,"FAIL")+COUNTIF('Engine-FY'!B37,"FAIL")+COUNTIF('Engine-FY'!C37,"FAIL")+COUNTIF('Engine-FY'!D37,"FAIL")+COUNTIF('Engine-FY'!B38,"FAIL")+COUNTIF('Engine-FY'!C38,"FAIL")+COUNTIF('Engine-FY'!D38,"FAIL")+COUNTIF('Engine-FY'!F42,"FAIL")+COUNTIF('Engine-FY'!B43,"FAIL")+COUNTIF('Engine-FY'!C43,"FAIL")+COUNTIF('Engine-FY'!D43,"FAIL")+COUNTIF('Engine-FY'!F46,"FAIL")+COUNTIF('Engine-FY'!F47,"FAIL")+COUNTIF('Engine-FY'!F48,"FAIL")+COUNTIF('Engine-FY'!F49,"FAIL")+COUNTIF('Engine-FY'!F50,"FAIL")+COUNTIF('Engine-FY'!F52,"FAIL")+COUNTIF('Engine-FY'!B53,"FAIL")+COUNTIF('Engine-FY'!C53,"FAIL")+COUNTIF('Engine-FY'!D53,"FAIL")+COUNTIF('Engine-FY'!C54,"FAIL")+COUNTIF('Engine-FY'!D54,"FAIL")+COUNTIF('Engine-FY'!F57,"FAIL")+COUNTIF('Engine-FY'!F58,"FAIL")+COUNTIF('Engine-FY'!F59,"FAIL")+COUNTIF('Engine-FY'!F60,"FAIL")+COUNTIF('Engine-FY'!F61,"FAIL")+COUNTIF('Engine-FY'!F63,"FAIL")+COUNTIF('Engine-FY'!B64,"FAIL")+COUNTIF('Engine-FY'!C64,"FAIL")+COUNTIF('Engine-FY'!D64,"FAIL")+COUNTIF('Engine-FY'!F67,"FAIL")+COUNTIF('Engine-FY'!F68,"FAIL")+COUNTIF('Engine-FY'!F70,"FAIL")+COUNTIF('Engine-FY'!F71,"FAIL")+COUNTIF('Engine-FY'!F72,"FAIL")+COUNTIF('Engine-FY'!F73,"FAIL")+COUNTIF('Engine-FY'!F75,"FAIL")+COUNTIF('Engine-FY'!B76,"FAIL")+COUNTIF('Engine-FY'!C76,"FAIL")+COUNTIF('Engine-FY'!D76,"FAIL")+COUNTIF('Engine-FY'!F79,"FAIL")+COUNTIF('Engine-FY'!F80,"FAIL")+COUNTIF('Engine-FY'!F82,"FAIL")+COUNTIF('Engine-FY'!F83,"FAIL")+COUNTIF('Engine-FY'!F85,"FAIL")+COUNTIF('Engine-FY'!B86,"FAIL")+COUNTIF('Engine-FY'!C86,"FAIL")+COUNTIF('Engine-FY'!D86,"FAIL")+COUNTIF('Engine-FY'!F87,"FAIL")+COUNTIF('Engine-FY'!F88,"FAIL")+COUNTIF('Engine-FY'!F90,"FAIL")+COUNTIF('Engine-FY'!B91,"FAIL")+COUNTIF('Engine-FY'!C91,"FAIL")+COUNTIF('Engine-FY'!D91,"FAIL")+COUNTIF('Engine-FY'!F102,"FAIL")+COUNTIF('Engine-FY'!F103,"FAIL")+COUNTIF('Engine-FY'!B106,"FAIL")+COUNTIF('Engine-FY'!C106,"FAIL")+COUNTIF('Engine-FY'!D106,"FAIL")+COUNTIF('Engine-FY'!F109,"FAIL")+COUNTIF('Engine-FY'!F110,"FAIL")+COUNTIF('Engine-FY'!F111,"FAIL")+COUNTIF('Engine-FY'!F112,"FAIL")+COUNTIF('Engine-FY'!B113,"FAIL")+COUNTIF('Engine-FY'!C113,"FAIL")+COUNTIF('Engine-FY'!D113,"FAIL")+COUNTIF('Engine-FY'!F114,"FAIL")+COUNTIF('Engine-FY'!F115,"FAIL")+COUNTIF('Engine-FY'!F116,"FAIL")+COUNTIF('Engine-FY'!F117,"FAIL")+COUNTIF('Engine-FY'!F118,"FAIL")+COUNTIF('Engine-FY'!F119,"FAIL")+COUNTIF('Engine-FY'!B120,"FAIL")+COUNTIF('Engine-FY'!C120,"FAIL")+COUNTIF('Engine-FY'!D120,"FAIL")+COUNTIF('Engine-FY'!F122,"FAIL")+COUNTIF('Engine-FY'!F123,"FAIL")+COUNTIF('Engine-FY'!F124,"FAIL")+COUNTIF('Engine-FY'!B127,"FAIL")+COUNTIF('Engine-FY'!C127,"FAIL")+COUNTIF('Engine-FY'!D127,"FAIL")+COUNTIF('Engine-FY'!F130,"FAIL")+COUNTIF('Engine-FY'!F131,"FAIL")+COUNTIF('Engine-FY'!F133,"FAIL")+COUNTIF('Engine-FY'!F134,"FAIL")+COUNTIF('Engine-FY'!F135,"FAIL")+COUNTIF('Engine-FY'!F136,"FAIL")+COUNTIF('Engine-FY'!F138,"FAIL")+COUNTIF('Engine-FY'!F139,"FAIL")+COUNTIF('Engine-FY'!F140,"FAIL")+COUNTIF('Engine-FY'!F141,"FAIL")+COUNTIF('Engine-FY'!F142,"FAIL")+COUNTIF('Engine-FY'!F143,"FAIL")+COUNTIF('Engine-FY'!F145,"FAIL")+COUNTIF('Engine-FY'!F146,"FAIL")+COUNTIF('Engine-FY'!F148,"FAIL")+COUNTIF('Engine-FY'!B149,"FAIL")+COUNTIF('Engine-FY'!C149,"FAIL")+COUNTIF('Engine-FY'!D149,"FAIL")+COUNTIF('Engine-FY'!F152,"FAIL")+COUNTIF('Engine-FY'!F153,"FAIL")+COUNTIF('Engine-FY'!F154,"FAIL")+COUNTIF('Engine-FY'!F156,"FAIL")+COUNTIF('Engine-FY'!F157,"FAIL")+COUNTIF('Engine-FY'!F158,"FAIL")+COUNTIF('Engine-FY'!F159,"FAIL")+COUNTIF('Engine-FY'!F160,"FAIL")+COUNTIF('Engine-FY'!F163,"FAIL")+COUNTIF('Engine-FY'!B164,"FAIL")+COUNTIF('Engine-FY'!C164,"FAIL")+COUNTIF('Engine-FY'!D164,"FAIL")+COUNTIF('Engine-FY'!F167,"FAIL")+COUNTIF('Engine-FY'!F168,"FAIL")+COUNTIF('Engine-FY'!F169,"FAIL")+COUNTIF('Engine-FY'!F170,"FAIL")+COUNTIF('Engine-FY'!F171,"FAIL")+COUNTIF('Engine-FY'!F172,"FAIL")+COUNTIF('Engine-FY'!F173,"FAIL")+COUNTIF('Engine-FY'!F175,"FAIL")+COUNTIF('Engine-FY'!B176,"FAIL")+COUNTIF('Engine-FY'!C176,"FAIL")+COUNTIF('Engine-FY'!D176,"FAIL")+COUNTIF('Engine-FY'!F177,"FAIL")+COUNTIF('Engine-FY'!F178,"FAIL")+COUNTIF('Engine-FY'!F179,"FAIL")+COUNTIF('Engine-FY'!F180,"FAIL")+COUNTIF('Engine-FY'!F181,"FAIL")+COUNTIF('Engine-FY'!F183,"FAIL")+COUNTIF('Engine-FY'!F185,"FAIL")+COUNTIF('Engine-FY'!F187,"FAIL")+COUNTIF('Engine-FY'!B188,"FAIL")+COUNTIF('Engine-FY'!C188,"FAIL")+COUNTIF('Engine-FY'!D188,"FAIL")+COUNTIF('Engine-FY'!F189,"FAIL")+COUNTIF('Engine-FY'!F190,"FAIL")+COUNTIF('Engine-FY'!F191,"FAIL")+COUNTIF('Engine-FY'!F193,"FAIL")+COUNTIF('Engine-FY'!B194,"FAIL")+COUNTIF('Engine-FY'!C194,"FAIL")+COUNTIF('Engine-FY'!D194,"FAIL")+COUNTIF('Engine-FY'!F197,"FAIL")+COUNTIF('Engine-FY'!F198,"FAIL")+COUNTIF('Engine-FY'!F199,"FAIL")+COUNTIF('Engine-FY'!F201,"FAIL")+COUNTIF('Engine-FY'!B202,"FAIL")+COUNTIF('Engine-FY'!C202,"FAIL")+COUNTIF('Engine-FY'!D202,"FAIL")+COUNTIF('Engine-FY'!F203,"FAIL")+COUNTIF('Engine-FY'!F205,"FAIL")+COUNTIF('Engine-FY'!B206,"FAIL")+COUNTIF('Engine-FY'!C206,"FAIL")+COUNTIF('Engine-FY'!D206,"FAIL")
A5: Checks watched: 316 cells — totals cross-cuts, rollforward identities, continuity, SRE chain, derived spread, and the quarterly-vs-annual source audit.

Sheet Data
A1: period | B1: metric | C1: value | D1: source
A2: 1Q25 | B2: acra_begin | C2: 72164 | D2: supplement
A3: 1Q25 | B3: acra_end | C3: 76842 | D3: supplement
A4: 1Q25 | B4: acra_inflows | C4: 5011 | D4: supplement
A5: 1Q25 | B5: acra_other | C5: 1042 | D5: supplement
A6: 1Q25 | B6: acra_own | C6: 0 | D6: supplement
A7: 1Q25 | B7: acra_withdrawals | C7: -1375 | D7: supplement
A8: 1Q25 | B8: avg_nia | C8: 255505 | D8: supplement
A9: 1Q25 | B9: avg_nia_alt | C9: 12506 | D9: supplement
A10: 1Q25 | B10: avg_nia_fi | C10: 242999 | D10: supplement
A11: 1Q25 | B11: core_outflows | C11: -7017 | D11: supplement
A12: 1Q25 | B12: flow_reins | C12: 4933 | D12: supplement
A13: 1Q25 | B13: funding_agreements | C13: 11144 | D13: supplement
... A939: FY2025 | B939: stat:cliff_2C:other | C939: 140359.7 | D939: statutory D1 (footed)

Sheet ReadMe
A1: ATHENE ENGINE WORKBOOK — README
A3: TABS: Engine = quarterly (4Q24–1Q26 + yellow 2Q26 fill column). Engine-FY = the SAME rows annually
A4: (FY2023–FY2025) with a live "FY25 Σ quarters" audit column. Checks must read 0. Data = raw extracted cells.
A6: SOURCES: ATH Q4 2025 + Q1 2026 Financial Supplements (quarterly + full-year YTD columns) and the AHL 10-K
A7: FY2025 MD&A (annual comparatives incl. FY2023). URLs + sha256 in acquisition/manifest.csv. Every blue cell
A8: was machine-extracted and passed exact cross-foot gates; the two sources were gated equal where they overlap.
A9: Extractors: tools/parse_fin_supplement.py, tools/parse_10k_annual_tables.py.
A11: LEGEND: blue = filed value · black bold = formula (recalculates in Excel) · grey = checks ("FAIL"/"n/a")
A12: · yellow = fill-in. Blank FY2023 cells: those rows are published only in supplements, and the 2023-era
A13: supplements are glyph-encoded (decoder parked). Blanks are honest gaps, not zeros.
A15: READ THE TREND: cost of funds $5,650M (FY23) → $7,702M → $10,083M (FY25), +78% in two years, while net
A16: investment earnings grew 49%; NIS margin 1.65% (1Q25) → 1.34% (1Q26); SRE margin below 1% in 1Q26.
A17: Volume is outrunning margin, and the margin is losing.
